qilimanjaroq_server/__init__.py
qilimanjaroq_server/config.py
qilimanjaroq_server/job_manager.py
qilimanjaroq_server/program.py
qilimanjaroq_server/util.py
qilimanjaroq_server/algorithm/__init__.py
qilimanjaroq_server/algorithm/algorithm.py
qilimanjaroq_server/algorithm/algorithm_manager.py
qilimanjaroq_server/algorithm/bellstate.py
qilimanjaroq_server/algorithm/bellstate_algorithm_manager.py
qilimanjaroq_server/tests/__init__.py
qilimanjaroq_server/tests/test_job_manager.py
qilimanjaroq_server/typings/__init__.py
qilimanjaroq_server/typings/algorithm.py
qilimanjaroq_server/typings/job.py
qilimanjaroq_server-0.0.2.dist-info/LICENSE
qilimanjaroq_server-0.0.2.dist-info/METADATA
qilimanjaroq_server-0.0.2.dist-info/WHEEL
qilimanjaroq_server-0.0.2.dist-info/top_level.txt
qilimanjaroq_server-0.0.2.dist-info/RECORD
