Metadata-Version: 2.1
Name: qilimanjaroq-server
Version: 0.0.2
Summary: Qilimanjaro server library to connect to the Qilimanjaro Quantum Service and use their devices
Home-page: https://github.com/qilimanjaro-tech/qili-qibo-backend
Author: Qilimanjaro team
Author-email: info@qilimanjaro.tech
License: UNKNOWN
Platform: UNKNOWN
Classifier: Programming Language :: Python :: 3
Classifier: Topic :: Scientific/Engineering :: Physics
Requires-Python: >=3.6.0
License-File: LICENSE
Requires-Dist: qibo
Requires-Dist: requests
Provides-Extra: docs
Requires-Dist: sphinx ; extra == 'docs'
Requires-Dist: sphinx-rtd-theme ; extra == 'docs'
Requires-Dist: recommonmark ; extra == 'docs'
Requires-Dist: sphinxcontrib-bibtex ; extra == 'docs'
Requires-Dist: sphinx-markdown-tables ; extra == 'docs'
Requires-Dist: nbsphinx ; extra == 'docs'
Requires-Dist: IPython ; extra == 'docs'
Provides-Extra: tests
Requires-Dist: pytest ; extra == 'tests'
